pymongo_curd/__init__.py
pymongo_curd/pymongo_curd.py
pymongo_curd-0.0.1.dist-info/LICENSE
pymongo_curd-0.0.1.dist-info/METADATA
pymongo_curd-0.0.1.dist-info/WHEEL
pymongo_curd-0.0.1.dist-info/top_level.txt
pymongo_curd-0.0.1.dist-info/RECORD
