Metadata-Version: 2.1
Name: pymongo-curd
Version: 0.0.1
Summary: pymongo 的一级文档及二级文档的CURD简单封装
Home-page: https://github.com/watele0528/mypackage.git
Author: Guomq
Author-email: Guo_mq@outlook.com
Requires-Python: >=3.8
License-File: LICENSE
